./.gitignore
./PKG-INFO
./README.md
./py.typed
./pyproject.toml
./example/README.md
./example/__init__.py
./example/moondream_vlm_example.py
./example/pyproject.toml
./tests/test_moondream.py
./tests/test_moondream_local.py
./tests/test_moondream_local_vlm.py
./tests/test_moondream_vlm.py
./vision_agents/plugins/moondream/__init__.py
./vision_agents/plugins/moondream/moondream_utils.py
./vision_agents/plugins/moondream/detection/moondream_cloud_processor.py
./vision_agents/plugins/moondream/detection/moondream_local_processor.py
./vision_agents/plugins/moondream/detection/moondream_video_track.py
./vision_agents/plugins/moondream/vlm/moondream_cloud_vlm.py
./vision_agents/plugins/moondream/vlm/moondream_local_vlm.py
vision_agents/plugins/moondream/__init__.py
vision_agents/plugins/moondream/moondream_utils.py
vision_agents/plugins/moondream/detection/moondream_cloud_processor.py
vision_agents/plugins/moondream/detection/moondream_local_processor.py
vision_agents/plugins/moondream/detection/moondream_video_track.py
vision_agents/plugins/moondream/vlm/moondream_cloud_vlm.py
vision_agents/plugins/moondream/vlm/moondream_local_vlm.py
vision_agents_plugins_moondream-0.2.10.dist-info/METADATA
vision_agents_plugins_moondream-0.2.10.dist-info/WHEEL
vision_agents_plugins_moondream-0.2.10.dist-info/RECORD
