Metadata-Version: 2.4
Name: vision-agents-plugins-moondream
Version: 0.2.10
Summary: Moondream 3 vision processor plugin for Vision Agents
Project-URL: Documentation, https://visionagents.ai/
Project-URL: Website, https://visionagents.ai/
Project-URL: Source, https://github.com/GetStream/Vision-Agents
License-Expression: MIT
Requires-Python: >=3.10
Requires-Dist: accelerate>=0.20.0
Requires-Dist: moondream>=0.1.1
Requires-Dist: numpy>=2.0.0
Requires-Dist: opencv-python>=4.8.0
Requires-Dist: pillow>=10.4.0
Requires-Dist: torch>=2.0.0
Requires-Dist: transformers>=4.40.0
Requires-Dist: vision-agents
